fw_gear_ants_dbm_cross_sectional/__init__.py
fw_gear_ants_dbm_cross_sectional/interfaces.py
fw_gear_ants_dbm_cross_sectional/main.py
fw_gear_ants_dbm_cross_sectional/parser.py
fw_gear_ants_dbm_cross_sectional/templates/OASIS-30_Atropos_template/Priors2/priors1.nii.gz
fw_gear_ants_dbm_cross_sectional/templates/OASIS-30_Atropos_template/Priors2/priors2.nii.gz
fw_gear_ants_dbm_cross_sectional/templates/OASIS-30_Atropos_template/Priors2/priors3.nii.gz
fw_gear_ants_dbm_cross_sectional/templates/OASIS-30_Atropos_template/Priors2/priors4.nii.gz
fw_gear_ants_dbm_cross_sectional/templates/OASIS-30_Atropos_template/Priors2/priors5.nii.gz
fw_gear_ants_dbm_cross_sectional/templates/OASIS-30_Atropos_template/Priors2/priors6.nii.gz
fw_gear_ants_dbm_cross_sectional/templates/OASIS-30_Atropos_template/brain_extraction_probability_mask/T_template0_BrainCerebellumProbabilityMask.nii.gz
fw_gear_ants_dbm_cross_sectional/templates/OASIS-30_Atropos_template/brain_segmentation_template/T_template0.nii.gz
fw_gear_ants_dbm_cross_sectional/templates/OASIS-30_Atropos_template/extraction_registration_mask/T_template0_BrainCerebellumMask.nii.gz
fw_gear_ants_dbm_cross_sectional/templates/OASIS-30_Atropos_template/t1_registration_template/T_template0_BrainCerebellum.nii.gz
fw_gear_ants_dbm_cross_sectional/utils.py
fw_gear_ants_dbm_cross_sectional/workflow.py
fw_gear_ants_dbm_cross_sectional-0.1.0.dist-info/LICENSE
fw_gear_ants_dbm_cross_sectional-0.1.0.dist-info/WHEEL
fw_gear_ants_dbm_cross_sectional-0.1.0.dist-info/METADATA
fw_gear_ants_dbm_cross_sectional-0.1.0.dist-info/RECORD
