Metadata-Version: 2.1
Name: fw-gear-ants-dbm-cross-sectional
Version: 0.1.0
Summary: 
Home-page: https://gitlab.com/flywheel-io/flywheel-apps/genentech/grp-43-ants-dbm-cross-sectional
License: MIT
Keywords: Flywheel,Gears
Author: Flywheel
Author-email: support@flywheel.io
Requires-Python: >=3.8,<4.0
Classifier: License :: OSI Approved :: MIT License
Classifier: Programming Language :: Python :: 3
Classifier: Programming Language :: Python :: 3.10
Classifier: Programming Language :: Python :: 3.8
Classifier: Programming Language :: Python :: 3.9
Classifier: Topic :: Scientific/Engineering
Requires-Dist: flywheel-gear-toolkit (>=0.5,<0.6)
Requires-Dist: flywheel-sdk (>=15.8.0,<15.9.0)
Requires-Dist: fw-utils (>=2.0.6,<3.0.0)
Requires-Dist: importlib (>=1.0.4,<2.0.0)
Requires-Dist: importlib-metadata (>=4.10.0,<5.0.0)
Requires-Dist: nipype (>=1.7.0,<2.0.0)
Project-URL: Repository, https://gitlab.com/flywheel-io/flywheel-apps/genentech/grp-43-ants-dbm-cross-sectional
